MANIFEST.in
README.rst
TITLE.txt
lh-agpl3-LICENSE.txt
setup.py
./bin/beamerExternalExtensions.py
./bin/screenstudioWebClientIcm.py
bisos2/__init__.py
bisos2.lcnt.egg-info/PKG-INFO
bisos2.lcnt.egg-info/SOURCES.txt
bisos2.lcnt.egg-info/dependency_links.txt
bisos2.lcnt.egg-info/namespace_packages.txt
bisos2.lcnt.egg-info/not-zip-safe
bisos2.lcnt.egg-info/requires.txt
bisos2.lcnt.egg-info/top_level.txt
bisos2/lcnt/__init__.py
bisos2/lcnt/beamerDisposition.py
bisos2/lcnt/impressiveSup.py
bisos2/lcnt/latexSup.py
bisos2/lcnt/screenstudioWebClient.py